[
  {
    "downloads": 21307721,
    "downloadsText": "21,307,721",
    "end": "2026-02-01",
    "owner": "unjs",
    "package": "unplugin",
    "provenance": "trusted",
    "start": "2026-01-26"
  },
  {
    "downloads": 8205673,
    "downloadsText": "8,205,673",
    "end": "2026-02-01",
    "owner": "sxzz",
    "package": "obug",
    "provenance": "trusted",
    "start": "2026-01-26"
  },
  {
    "downloads": 6881924,
    "downloadsText": "6,881,924",
    "end": "2026-02-01",
    "owner": "quansync-dev",
    "package": "quansync",
    "provenance": "trusted",
    "start": "2026-01-26"
  },
  {
    "downloads": 4232472,
    "downloadsText": "4,232,472",
    "end": "2026-02-01",
    "owner": "sxzz",
    "package": "unplugin-utils",
    "provenance": "trusted",
    "start": "2026-01-26"
  },
  {
    "downloads": 2312226,
    "downloadsText": "2,312,226",
    "end": "2026-02-01",
    "owner": "vuejs",
    "package": "@vue/babel-plugin-jsx",
    "provenance": "trusted",
    "start": "2026-01-26"
  },
  {
    "downloads": 2199811,
    "downloadsText": "2,199,811",
    "end": "2026-02-01",
    "owner": "sxzz",
    "package": "ast-kit",
    "provenance": "trusted",
    "start": "2026-01-26"
  },
  {
    "downloads": 1310319,
    "downloadsText": "1,310,319",
    "end": "2026-02-01",
    "owner": "vue-macros",
    "package": "@vue-macros/common",
    "provenance": "trusted",
    "start": "2026-01-26"
  },
  {
    "downloads": 1297965,
    "downloadsText": "1,297,965",
    "end": "2026-02-01",
    "owner": "sxzz",
    "package": "magic-string-ast",
    "provenance": "trusted",
    "start": "2026-01-26"
  },
  {
    "downloads": 1165511,
    "downloadsText": "1,165,511",
    "end": "2026-02-01",
    "owner": "sxzz",
    "package": "ast-walker-scope",
    "provenance": "trusted",
    "start": "2026-01-26"
  },
  {
    "downloads": 1000146,
    "downloadsText": "1,000,146",
    "end": "2026-02-01",
    "owner": "quansync-dev",
    "package": "@quansync/fs",
    "provenance": "trusted",
    "start": "2026-01-26"
  },
  {
    "downloads": 847350,
    "downloadsText": "847,350",
    "end": "2026-02-01",
    "owner": "sxzz",
    "package": "rolldown-plugin-dts",
    "provenance": "trusted",
    "start": "2026-01-26"
  },
  {
    "downloads": 807278,
    "downloadsText": "807,278",
    "end": "2026-02-01",
    "owner": "sxzz",
    "package": "dts-resolver",
    "provenance": "trusted",
    "start": "2026-01-26"
  },
  {
    "downloads": 748620,
    "downloadsText": "748,620",
    "end": "2026-02-01",
    "owner": "rolldown",
    "package": "tsdown",
    "provenance": "trusted",
    "start": "2026-01-26"
  },
  {
    "downloads": 405795,
    "downloadsText": "405,795",
    "end": "2026-02-01",
    "owner": "sxzz",
    "package": "import-without-cache",
    "provenance": "trusted",
    "start": "2026-01-26"
  },
  {
    "downloads": 138091,
    "downloadsText": "138,091",
    "end": "2026-02-01",
    "owner": "unplugin",
    "package": "unplugin-ast",
    "provenance": "trusted",
    "start": "2026-01-26"
  },
  {
    "downloads": 20743,
    "downloadsText": "20,743",
    "end": "2026-02-01",
    "owner": "unplugin",
    "package": "unplugin-isolated-decl",
    "provenance": "trusted",
    "start": "2026-01-26"
  },
  {
    "downloads": 19378,
    "downloadsText": "19,378",
    "end": "2026-02-01",
    "owner": "vuejs",
    "package": "@vue/repl",
    "provenance": "trusted",
    "start": "2026-01-26"
  },
  {
    "downloads": 18213,
    "downloadsText": "18,213",
    "end": "2026-02-01",
    "owner": "sxzz",
    "package": "unplugin-combine",
    "provenance": "trusted",
    "start": "2026-01-26"
  },
  {
    "downloads": 15842,
    "downloadsText": "15,842",
    "end": "2026-02-01",
    "owner": "unplugin",
    "package": "unplugin-lightningcss",
    "provenance": "trusted",
    "start": "2026-01-26"
  },
  {
    "downloads": 9364,
    "downloadsText": "9,364",
    "end": "2026-02-01",
    "owner": "sxzz",
    "package": "rolldown-string",
    "provenance": "trusted",
    "start": "2026-01-26"
  },
  {
    "downloads": 9038,
    "downloadsText": "9,038",
    "end": "2026-02-01",
    "owner": "unplugin",
    "package": "unplugin-unused",
    "provenance": "trusted",
    "start": "2026-01-26"
  },
  {
    "downloads": 8315,
    "downloadsText": "8,315",
    "end": "2026-02-01",
    "owner": "unplugin",
    "package": "unplugin-replace",
    "provenance": "trusted",
    "start": "2026-01-26"
  },
  {
    "downloads": 8183,
    "downloadsText": "8,183",
    "end": "2026-02-02",
    "owner": "unplugin",
    "package": "unplugin-vue",
    "provenance": "trusted",
    "start": "2026-01-27"
  },
  {
    "downloads": 6141,
    "downloadsText": "6,141",
    "end": "2026-02-01",
    "owner": "unplugin",
    "package": "unplugin-raw",
    "provenance": "trusted",
    "start": "2026-01-26"
  },
  {
    "downloads": 5064,
    "downloadsText": "5,064",
    "end": "2026-02-01",
    "owner": "sxzz",
    "package": "@sxzz/eslint-config",
    "provenance": "trusted",
    "start": "2026-01-26"
  },
  {
    "downloads": 4724,
    "downloadsText": "4,724",
    "end": "2026-02-01",
    "owner": "sxzz",
    "package": "eslint-plugin-sxzz",
    "provenance": "trusted",
    "start": "2026-01-26"
  },
  {
    "downloads": 4633,
    "downloadsText": "4,633",
    "end": "2026-02-01",
    "owner": "unplugin",
    "package": "unplugin-oxc",
    "provenance": "trusted",
    "start": "2026-01-26"
  },
  {
    "downloads": 4449,
    "downloadsText": "4,449",
    "end": "2026-02-02",
    "owner": "vue-macros",
    "package": "vue-macros",
    "provenance": "trusted",
    "start": "2026-01-27"
  },
  {
    "downloads": 3593,
    "downloadsText": "3,593",
    "end": "2026-02-01",
    "owner": "sxzz",
    "package": "@sxzz/prettier-config",
    "provenance": "trusted",
    "start": "2026-01-26"
  },
  {
    "downloads": 3356,
    "downloadsText": "3,356",
    "end": "2026-02-01",
    "owner": "unplugin",
    "package": "unplugin-macros",
    "provenance": "trusted",
    "start": "2026-01-26"
  },
  {
    "downloads": 3332,
    "downloadsText": "3,332",
    "end": "2026-02-01",
    "owner": "sxzz",
    "package": "eslint-plugin-importer",
    "provenance": "trusted",
    "start": "2026-01-26"
  },
  {
    "downloads": 2177,
    "downloadsText": "2,177",
    "end": "2026-02-01",
    "owner": "sxzz",
    "package": "tsgo-wasm",
    "provenance": "trusted",
    "start": "2026-01-26"
  },
  {
    "downloads": 2027,
    "downloadsText": "2,027",
    "end": "2026-02-02",
    "owner": "unplugin",
    "package": "unplugin-vue-jsx",
    "provenance": "trusted",
    "start": "2026-01-27"
  },
  {
    "downloads": 1783,
    "downloadsText": "1,783",
    "end": "2026-02-01",
    "owner": "sxzz",
    "package": "@sxzz/test-utils",
    "provenance": "trusted",
    "start": "2026-01-26"
  },
  {
    "downloads": 1169,
    "downloadsText": "1,169",
    "end": "2026-02-01",
    "owner": "sxzz",
    "package": "unloader",
    "provenance": "trusted",
    "start": "2026-01-26"
  },
  {
    "downloads": 984,
    "downloadsText": "984",
    "end": "2026-02-01",
    "owner": "sxzz",
    "package": "tsdown-preset-sxzz",
    "provenance": "trusted",
    "start": "2026-01-26"
  },
  {
    "downloads": 908,
    "downloadsText": "908",
    "end": "2026-02-02",
    "owner": "sxzz",
    "package": "vite-hyper-config",
    "provenance": "trusted",
    "start": "2026-01-27"
  },
  {
    "downloads": 764,
    "downloadsText": "764",
    "end": "2026-02-01",
    "owner": "sxzz",
    "package": "stale-dep",
    "provenance": "trusted",
    "start": "2026-01-26"
  },
  {
    "downloads": 513,
    "downloadsText": "513",
    "end": "2026-02-01",
    "owner": "sxzz",
    "package": "pnpm-multi-versions",
    "provenance": "trusted",
    "start": "2026-01-26"
  },
  {
    "downloads": 386,
    "downloadsText": "386",
    "end": "2026-02-01",
    "owner": "sxzz",
    "package": "rolldown-plugin-require-cjs",
    "provenance": "trusted",
    "start": "2026-01-26"
  },
  {
    "downloads": 309,
    "downloadsText": "309",
    "end": "2026-02-01",
    "owner": "sxzz",
    "package": "rolldown-plugin-dts-snapshot",
    "provenance": "trusted",
    "start": "2026-01-26"
  },
  {
    "downloads": 189,
    "downloadsText": "189",
    "end": "2026-02-01",
    "owner": "quansync-dev",
    "package": "unplugin-quansync",
    "provenance": "trusted",
    "start": "2026-01-26"
  },
  {
    "downloads": 163,
    "downloadsText": "163",
    "end": "2026-02-02",
    "owner": "sxzz",
    "package": "untsx",
    "provenance": "trusted",
    "start": "2026-01-27"
  },
  {
    "downloads": 152,
    "downloadsText": "152",
    "end": "2026-02-01",
    "owner": "unplugin",
    "package": "unplugin-inline-enum",
    "provenance": "trusted",
    "start": "2026-01-26"
  },
  {
    "downloads": 132,
    "downloadsText": "132",
    "end": "2026-02-01",
    "owner": "sxzz",
    "package": "monoman",
    "provenance": "trusted",
    "start": "2026-01-26"
  },
  {
    "downloads": 82,
    "downloadsText": "82",
    "end": "2026-02-02",
    "owner": "unplugin",
    "package": "unplugin-vue-named-export",
    "provenance": "trusted",
    "start": "2026-01-27"
  },
  {
    "downloads": 78,
    "downloadsText": "78",
    "end": "2026-02-01",
    "owner": "sxzz",
    "package": "tc39-try",
    "provenance": "trusted",
    "start": "2026-01-26"
  },
  {
    "downloads": 75,
    "downloadsText": "75",
    "end": "2026-02-01",
    "owner": "unplugin",
    "package": "unplugin-jsx-string",
    "provenance": "trusted",
    "start": "2026-01-26"
  },
  {
    "downloads": 74,
    "downloadsText": "74",
    "end": "2026-02-01",
    "owner": "sxzz",
    "package": "@sxzz/create",
    "provenance": "trusted",
    "start": "2026-01-26"
  },
  {
    "downloads": 68,
    "downloadsText": "68",
    "end": "2026-02-01",
    "owner": "sxzz",
    "package": "rolldown-plugin-wasm",
    "provenance": "trusted",
    "start": "2026-01-26"
  },
  {
    "downloads": 55,
    "downloadsText": "55",
    "end": "2026-02-02",
    "owner": "sxzz",
    "package": "vue-simple-props",
    "provenance": "trusted",
    "start": "2026-01-27"
  },
  {
    "downloads": 54,
    "downloadsText": "54",
    "end": "2026-02-02",
    "owner": "sxzz",
    "package": "vue-functional-ref",
    "provenance": "trusted",
    "start": "2026-01-27"
  },
  {
    "downloads": 53,
    "downloadsText": "53",
    "end": "2026-02-01",
    "owner": "sxzz",
    "package": "tc39-throw",
    "provenance": "trusted",
    "start": "2026-01-26"
  }
]
