[
  {
    "downloads": 24678247,
    "downloadsText": "24,678,247",
    "end": "2026-03-14",
    "owner": "cacjs",
    "package": "cac",
    "provenance": "trusted",
    "start": "2026-03-08"
  },
  {
    "downloads": 21356504,
    "downloadsText": "21,356,504",
    "end": "2026-03-14",
    "owner": "unjs",
    "package": "unplugin",
    "provenance": "trusted",
    "start": "2026-03-08"
  },
  {
    "downloads": 12938623,
    "downloadsText": "12,938,623",
    "end": "2026-03-14",
    "owner": "sxzz",
    "package": "obug",
    "provenance": "trusted",
    "start": "2026-03-08"
  },
  {
    "downloads": 7665147,
    "downloadsText": "7,665,147",
    "end": "2026-03-14",
    "owner": "quansync-dev",
    "package": "quansync",
    "provenance": "trusted",
    "start": "2026-03-08"
  },
  {
    "downloads": 4204817,
    "downloadsText": "4,204,817",
    "end": "2026-03-14",
    "owner": "sxzz",
    "package": "unplugin-utils",
    "provenance": "trusted",
    "start": "2026-03-08"
  },
  {
    "downloads": 2916101,
    "downloadsText": "2,916,101",
    "end": "2026-03-14",
    "owner": "sxzz",
    "package": "ast-kit",
    "provenance": "trusted",
    "start": "2026-03-08"
  },
  {
    "downloads": 2510300,
    "downloadsText": "2,510,300",
    "end": "2026-03-14",
    "owner": "vuejs",
    "package": "@vue/babel-plugin-jsx",
    "provenance": "trusted",
    "start": "2026-03-08"
  },
  {
    "downloads": 1590271,
    "downloadsText": "1,590,271",
    "end": "2026-03-14",
    "owner": "vue-macros",
    "package": "@vue-macros/common",
    "provenance": "trusted",
    "start": "2026-03-08"
  },
  {
    "downloads": 1585485,
    "downloadsText": "1,585,485",
    "end": "2026-03-14",
    "owner": "sxzz",
    "package": "magic-string-ast",
    "provenance": "trusted",
    "start": "2026-03-08"
  },
  {
    "downloads": 1493373,
    "downloadsText": "1,493,373",
    "end": "2026-03-14",
    "owner": "sxzz",
    "package": "ast-walker-scope",
    "provenance": "trusted",
    "start": "2026-03-08"
  },
  {
    "downloads": 1456949,
    "downloadsText": "1,456,949",
    "end": "2026-03-14",
    "owner": "quansync-dev",
    "package": "@quansync/fs",
    "provenance": "trusted",
    "start": "2026-03-08"
  },
  {
    "downloads": 1420879,
    "downloadsText": "1,420,879",
    "end": "2026-03-14",
    "owner": "sxzz",
    "package": "rolldown-plugin-dts",
    "provenance": "trusted",
    "start": "2026-03-08"
  },
  {
    "downloads": 1313926,
    "downloadsText": "1,313,926",
    "end": "2026-03-14",
    "owner": "rolldown",
    "package": "tsdown",
    "provenance": "trusted",
    "start": "2026-03-08"
  },
  {
    "downloads": 1273196,
    "downloadsText": "1,273,196",
    "end": "2026-03-14",
    "owner": "sxzz",
    "package": "dts-resolver",
    "provenance": "trusted",
    "start": "2026-03-08"
  },
  {
    "downloads": 883290,
    "downloadsText": "883,290",
    "end": "2026-03-14",
    "owner": "sxzz",
    "package": "import-without-cache",
    "provenance": "trusted",
    "start": "2026-03-08"
  },
  {
    "downloads": 88181,
    "downloadsText": "88,181",
    "end": "2026-03-14",
    "owner": "unplugin",
    "package": "unplugin-ast",
    "provenance": "trusted",
    "start": "2026-03-08"
  },
  {
    "downloads": 43662,
    "downloadsText": "43,662",
    "end": "2026-03-14",
    "owner": "unplugin",
    "package": "unplugin-isolated-decl",
    "provenance": "trusted",
    "start": "2026-03-08"
  },
  {
    "downloads": 24054,
    "downloadsText": "24,054",
    "end": "2026-03-14",
    "owner": "sxzz",
    "package": "unplugin-combine",
    "provenance": "trusted",
    "start": "2026-03-08"
  },
  {
    "downloads": 20846,
    "downloadsText": "20,846",
    "end": "2026-03-14",
    "owner": "unplugin",
    "package": "unplugin-unused",
    "provenance": "trusted",
    "start": "2026-03-08"
  },
  {
    "downloads": 17170,
    "downloadsText": "17,170",
    "end": "2026-03-14",
    "owner": "unplugin",
    "package": "unplugin-lightningcss",
    "provenance": "trusted",
    "start": "2026-03-08"
  },
  {
    "downloads": 16347,
    "downloadsText": "16,347",
    "end": "2026-03-14",
    "owner": "unplugin",
    "package": "unplugin-vue",
    "provenance": "trusted",
    "start": "2026-03-08"
  },
  {
    "downloads": 9777,
    "downloadsText": "9,777",
    "end": "2026-03-14",
    "owner": "vuejs",
    "package": "@vue/repl",
    "provenance": "trusted",
    "start": "2026-03-08"
  },
  {
    "downloads": 8874,
    "downloadsText": "8,874",
    "end": "2026-03-14",
    "owner": "unplugin",
    "package": "unplugin-oxc",
    "provenance": "trusted",
    "start": "2026-03-08"
  },
  {
    "downloads": 8623,
    "downloadsText": "8,623",
    "end": "2026-03-14",
    "owner": "vue-macros",
    "package": "vue-macros",
    "provenance": "trusted",
    "start": "2026-03-08"
  },
  {
    "downloads": 7762,
    "downloadsText": "7,762",
    "end": "2026-03-14",
    "owner": "unplugin",
    "package": "unplugin-raw",
    "provenance": "trusted",
    "start": "2026-03-08"
  },
  {
    "downloads": 6952,
    "downloadsText": "6,952",
    "end": "2026-03-14",
    "owner": "sxzz",
    "package": "rolldown-string",
    "provenance": "trusted",
    "start": "2026-03-08"
  },
  {
    "downloads": 5200,
    "downloadsText": "5,200",
    "end": "2026-03-14",
    "owner": "sxzz",
    "package": "@sxzz/eslint-config",
    "provenance": "trusted",
    "start": "2026-03-08"
  },
  {
    "downloads": 4977,
    "downloadsText": "4,977",
    "end": "2026-03-14",
    "owner": "sxzz",
    "package": "eslint-plugin-sxzz",
    "provenance": "trusted",
    "start": "2026-03-08"
  },
  {
    "downloads": 4367,
    "downloadsText": "4,367",
    "end": "2026-03-14",
    "owner": "sxzz",
    "package": "@sxzz/prettier-config",
    "provenance": "trusted",
    "start": "2026-03-08"
  },
  {
    "downloads": 4342,
    "downloadsText": "4,342",
    "end": "2026-03-14",
    "owner": "unplugin",
    "package": "unplugin-macros",
    "provenance": "trusted",
    "start": "2026-03-08"
  },
  {
    "downloads": 4038,
    "downloadsText": "4,038",
    "end": "2026-03-14",
    "owner": "sxzz",
    "package": "eslint-plugin-importer",
    "provenance": "trusted",
    "start": "2026-03-08"
  },
  {
    "downloads": 3444,
    "downloadsText": "3,444",
    "end": "2026-03-14",
    "owner": "unplugin",
    "package": "unplugin-replace",
    "provenance": "trusted",
    "start": "2026-03-08"
  },
  {
    "downloads": 2914,
    "downloadsText": "2,914",
    "end": "2026-03-14",
    "owner": "sxzz",
    "package": "@sxzz/test-utils",
    "provenance": "trusted",
    "start": "2026-03-08"
  },
  {
    "downloads": 1871,
    "downloadsText": "1,871",
    "end": "2026-03-14",
    "owner": "sxzz",
    "package": "tsdown-preset-sxzz",
    "provenance": "trusted",
    "start": "2026-03-08"
  },
  {
    "downloads": 1678,
    "downloadsText": "1,678",
    "end": "2026-03-14",
    "owner": "sxzz",
    "package": "pnpm-multi-versions",
    "provenance": "trusted",
    "start": "2026-03-08"
  },
  {
    "downloads": 1524,
    "downloadsText": "1,524",
    "end": "2026-03-14",
    "owner": "sxzz",
    "package": "vite-hyper-config",
    "provenance": "trusted",
    "start": "2026-03-08"
  },
  {
    "downloads": 1391,
    "downloadsText": "1,391",
    "end": "2026-03-14",
    "owner": "unplugin",
    "package": "unplugin-vue-jsx",
    "provenance": "trusted",
    "start": "2026-03-08"
  },
  {
    "downloads": 1211,
    "downloadsText": "1,211",
    "end": "2026-03-14",
    "owner": "sxzz",
    "package": "tsgo-wasm",
    "provenance": "trusted",
    "start": "2026-03-08"
  },
  {
    "downloads": 968,
    "downloadsText": "968",
    "end": "2026-03-14",
    "owner": "sxzz",
    "package": "stale-dep",
    "provenance": "trusted",
    "start": "2026-03-08"
  },
  {
    "downloads": 823,
    "downloadsText": "823",
    "end": "2026-03-14",
    "owner": "sxzz",
    "package": "rolldown-plugin-require-cjs",
    "provenance": "trusted",
    "start": "2026-03-08"
  },
  {
    "downloads": 504,
    "downloadsText": "504",
    "end": "2026-03-14",
    "owner": "sxzz",
    "package": "rolldown-plugin-dts-snapshot",
    "provenance": "trusted",
    "start": "2026-03-08"
  },
  {
    "downloads": 433,
    "downloadsText": "433",
    "end": "2026-03-14",
    "owner": "sxzz",
    "package": "unloader",
    "provenance": "trusted",
    "start": "2026-03-08"
  },
  {
    "downloads": 417,
    "downloadsText": "417",
    "end": "2026-03-14",
    "owner": "quansync-dev",
    "package": "unplugin-quansync",
    "provenance": "trusted",
    "start": "2026-03-08"
  },
  {
    "downloads": 339,
    "downloadsText": "339",
    "end": "2026-03-14",
    "owner": "sxzz",
    "package": "monoman",
    "provenance": "trusted",
    "start": "2026-03-08"
  },
  {
    "downloads": 290,
    "downloadsText": "290",
    "end": "2026-03-14",
    "owner": "sxzz",
    "package": "rolldown-plugin-wasm",
    "provenance": "trusted",
    "start": "2026-03-08"
  },
  {
    "downloads": 133,
    "downloadsText": "133",
    "end": "2026-03-14",
    "owner": "sxzz",
    "package": "@sxzz/create",
    "provenance": "trusted",
    "start": "2026-03-08"
  },
  {
    "downloads": 98,
    "downloadsText": "98",
    "end": "2026-03-14",
    "owner": "sxzz",
    "package": "untsx",
    "provenance": "trusted",
    "start": "2026-03-08"
  },
  {
    "downloads": 73,
    "downloadsText": "73",
    "end": "2026-03-14",
    "owner": "unplugin",
    "package": "unplugin-inline-enum",
    "provenance": "trusted",
    "start": "2026-03-08"
  },
  {
    "downloads": 45,
    "downloadsText": "45",
    "end": "2026-03-14",
    "owner": "sxzz",
    "package": "tc39-try",
    "provenance": "trusted",
    "start": "2026-03-08"
  },
  {
    "downloads": 29,
    "downloadsText": "29",
    "end": "2026-03-14",
    "owner": "sxzz",
    "package": "vue-simple-props",
    "provenance": "trusted",
    "start": "2026-03-08"
  },
  {
    "downloads": 28,
    "downloadsText": "28",
    "end": "2026-03-14",
    "owner": "sxzz",
    "package": "vue-functional-ref",
    "provenance": "trusted",
    "start": "2026-03-08"
  },
  {
    "downloads": 27,
    "downloadsText": "27",
    "end": "2026-03-14",
    "owner": "unplugin",
    "package": "unplugin-vue-named-export",
    "provenance": "trusted",
    "start": "2026-03-08"
  },
  {
    "downloads": 24,
    "downloadsText": "24",
    "end": "2026-03-14",
    "owner": "sxzz",
    "package": "tc39-throw",
    "provenance": "trusted",
    "start": "2026-03-08"
  },
  {
    "downloads": 24,
    "downloadsText": "24",
    "end": "2026-03-14",
    "owner": "unplugin",
    "package": "unplugin-jsx-string",
    "provenance": "trusted",
    "start": "2026-03-08"
  }
]
